<?xml version="1.0" encoding="UTF-8" standalone="yes"?>
<calcChain xmlns="http://schemas.openxmlformats.org/spreadsheetml/2006/main"><c r="X11" i="24" l="1"/><c r="AA11" i="24" l="1"/><c r="Z11" i="24"/><c r="Y11" i="24"/><c r="X12" i="24"/><c r="X13" i="24" s="1"/><c r="X14" i="24" s="1"/><c r="X15" i="24" s="1"/><c r="X16" i="24" s="1"/><c r="X17" i="24" s="1"/><c r="X18" i="24" s="1"/><c r="X19" i="24" s="1"/><c r="X20" i="24" s="1"/><c r="X21" i="24" s="1"/><c r="W13" i="24"/><c r="W12" i="24" s="1"/><c r="W11" i="24" s="1"/><c r="W15" i="24"/><c r="W14" i="24" s="1"/><c r="W16" i="24"/><c r="W17" i="24"/><c r="W18" i="24" s="1"/><c r="W19" i="24" s="1"/><c r="W20" i="24" s="1"/><c r="W21" i="24" s="1"/><c r="V11" i="24"/><c r="U18" i="24"/><c r="U17" i="24" s="1"/><c r="U16" i="24" s="1"/><c r="U15" i="24" s="1"/><c r="U14" i="24" s="1"/><c r="U13" i="24" s="1"/><c r="U12" i="24" s="1"/><c r="U11" i="24" s="1"/><c r="U21" i="24"/><c r="T11" i="24"/><c r="R21" i="24" l="1"/><c r="R20" i="24" s="1"/><c r="R19" i="24" s="1"/><c r="R18" i="24" s="1"/><c r="R17" i="24" s="1"/><c r="R16" i="24" s="1"/><c r="R15" i="24" s="1"/><c r="R14" i="24" s="1"/><c r="R13" i="24" s="1"/><c r="R12" i="24" s="1"/><c r="R11" i="24" s="1"/><c r="Q21" i="24"/><c r="Q20" i="24"/><c r="Q12" i="24"/><c r="Q13" i="24"/><c r="Q14" i="24"/><c r="Q15" i="24"/><c r="Q16" i="24" s="1"/><c r="Q17" i="24" s="1"/><c r="Q18" i="24" s="1"/><c r="Q19" i="24" s="1"/><c r="P21" i="24"/><c r="P20" i="24"/><c r="P19" i="24"/><c r="P18" i="24"/><c r="P17" i="24" s="1"/><c r="P16" i="24" s="1"/><c r="P15" i="24" s="1"/><c r="P14" i="24" s="1"/><c r="P13" i="24" s="1"/><c r="P12" i="24" s="1"/><c r="P11" i="24" s="1"/><c r="O11" i="24"/><c r="O12" i="24"/><c r="O13" i="24"/><c r="O14" i="24"/><c r="O16" i="24"/><c r="O15" i="24" s="1"/><c r="O17" i="24"/><c r="O18" i="24"/><c r="O19" i="24"/><c r="O20" i="24" s="1"/><c r="O21" i="24" s="1"/><c r="M11" i="24"/><c r="M18" i="24"/><c r="M17" i="24" s="1"/><c r="M16" i="24" s="1"/><c r="M15" i="24" s="1"/><c r="M14" i="24" s="1"/><c r="M13" i="24" s="1"/><c r="M12" i="24" s="1"/><c r="M19" i="24"/><c r="L18" i="24"/><c r="L17" i="24" s="1"/><c r="L16" i="24" s="1"/><c r="L15" i="24" s="1"/><c r="L14" i="24" s="1"/><c r="L13" i="24" s="1"/><c r="L12" i="24" s="1"/><c r="L11" i="24" s="1"/><c r="L19" i="24"/><c r="L20" i="24" s="1"/><c r="L21" i="24" s="1"/><c r="K11" i="24"/><c r="J14" i="24" l="1"/><c r="J13" i="24" s="1"/><c r="J12" i="24" s="1"/><c r="J11" i="24" s="1"/><c r="J15" i="24"/><c r="J16" i="24" s="1"/><c r="J17" i="24" s="1"/><c r="J18" i="24" s="1"/><c r="J19" i="24" s="1"/><c r="J20" i="24" s="1"/><c r="J21" i="24" s="1"/><c r="I18" i="24"/><c r="I21" i="24"/><c r="I20" i="24" s="1"/><c r="I19" i="24" s="1"/><c r="H12" i="24"/><c r="H11" i="24"/><c r="G14" i="24"/><c r="G13" i="24" s="1"/><c r="G12" i="24" s="1"/><c r="G11" i="24" s="1"/><c r="G16" i="24"/><c r="G15" i="24" s="1"/><c r="G17" i="24"/><c r="G18" i="24"/><c r="G21" i="24"/><c r="G20" i="24" s="1"/><c r="G19" i="24" s="1"/><c r="F14" i="24"/><c r="F13" i="24" s="1"/><c r="F12" i="24" s="1"/><c r="F11" i="24" s="1"/><c r="F16" i="24"/><c r="F15" i="24" s="1"/><c r="F17" i="24"/><c r="F18" i="24"/><c r="F21" i="24"/><c r="F20" i="24" s="1"/><c r="F19" i="24" s="1"/><c r="E14" i="24"/><c r="E13" i="24" s="1"/><c r="E12" i="24" s="1"/><c r="E11" i="24" s="1"/><c r="E16" i="24"/><c r="E15" i="24" s="1"/><c r="E17" i="24"/><c r="E18" i="24"/><c r="E20" i="24"/><c r="E19" i="24" s="1"/><c r="E21" i="24"/><c r="C19" i="24"/><c r="C18" i="24" s="1"/><c r="C17" i="24" s="1"/><c r="C16" i="24" s="1"/><c r="C15" i="24" s="1"/><c r="C14" i="24" s="1"/><c r="C13" i="24" s="1"/><c r="C12" i="24" s="1"/><c r="C11" i="24" s="1"/><c r="B18" i="24"/><c r="B17" i="24" s="1"/><c r="B16" i="24" s="1"/><c r="B15" i="24" s="1"/><c r="B14" i="24" s="1"/><c r="B13" i="24" s="1"/><c r="B12" i="24" s="1"/><c r="B11" i="24" s="1"/><c r="I17" i="24" l="1"/><c r="I16" i="24" s="1"/><c r="I15" i="24" s="1"/><c r="I14" i="24" s="1"/><c r="I13" i="24" s="1"/><c r="I12" i="24" s="1"/><c r="I11" i="24" s="1"/><c r="D11" i="24"/><c r="C20" i="24"/><c r="C21" i="24" s="1"/><c r="N11" i="24" l="1"/><c r="G21" i="26" l="1"/><c r="H21" i="26"/><c r="J12" i="26"/><c r="J13" i="26"/><c r="J14" i="26"/><c r="J15" i="26"/><c r="J16" i="26"/><c r="J17" i="26"/><c r="J18" i="26"/><c r="J19" i="26"/><c r="F12" i="26"/><c r="F13" i="26"/><c r="F14" i="26"/><c r="F15" i="26"/><c r="F16" i="26"/><c r="F17" i="26"/><c r="F18" i="26"/><c r="F19" i="26"/><c r="K12" i="26"/><c r="K13" i="26"/><c r="K14" i="26"/><c r="K15" i="26"/><c r="K16" i="26"/><c r="K17" i="26"/><c r="K18" i="26"/><c r="K19" i="26"/><c r="G12" i="26"/><c r="G13" i="26"/><c r="G14" i="26"/><c r="G15" i="26"/><c r="G16" i="26"/><c r="G17" i="26"/><c r="G18" i="26"/><c r="G19" i="26"/><c r="C12" i="26"/><c r="C13" i="26"/><c r="C14" i="26"/><c r="C15" i="26"/><c r="C16" i="26"/><c r="C17" i="26"/><c r="C18" i="26"/><c r="C19" i="26"/><c r="N12" i="26"/><c r="N13" i="26"/><c r="N14" i="26"/><c r="N15" i="26"/><c r="N16" i="26"/><c r="N17" i="26"/><c r="N18" i="26"/><c r="N19" i="26"/><c r="M12" i="26"/><c r="M13" i="26"/><c r="M14" i="26"/><c r="M15" i="26"/><c r="M16" i="26"/><c r="M17" i="26"/><c r="M18" i="26"/><c r="M19" i="26"/><c r="L12" i="26"/><c r="L13" i="26"/><c r="L14" i="26"/><c r="L15" i="26"/><c r="L16" i="26"/><c r="L17" i="26"/><c r="L18" i="26"/><c r="L19" i="26"/><c r="I12" i="26"/><c r="I13" i="26"/><c r="I14" i="26"/><c r="I15" i="26"/><c r="I16" i="26"/><c r="I17" i="26"/><c r="I18" i="26"/><c r="I19" i="26"/><c r="H12" i="26"/><c r="H13" i="26"/><c r="H14" i="26"/><c r="H15" i="26"/><c r="H16" i="26"/><c r="H17" i="26"/><c r="H18" i="26"/><c r="H19" i="26"/><c r="E12" i="26"/><c r="E13" i="26"/><c r="E14" i="26"/><c r="E15" i="26"/><c r="E16" i="26"/><c r="E17" i="26"/><c r="E18" i="26"/><c r="E19" i="26"/><c r="D12" i="26"/><c r="D13" i="26"/><c r="D14" i="26"/><c r="D15" i="26"/><c r="D16" i="26"/><c r="D17" i="26"/><c r="D18" i="26"/><c r="D19" i="26"/><c r="B12" i="26"/><c r="B13" i="26"/><c r="B14" i="26"/><c r="B15" i="26"/><c r="B16" i="26"/><c r="B17" i="26"/><c r="B18" i="26"/><c r="B19" i="26"/><c r="C18" i="25"/><c r="C16" i="25"/><c r="V13" i="25"/><c r="V14" i="25"/><c r="V15" i="25"/><c r="V16" i="25"/><c r="V17" i="25"/><c r="V18" i="25"/><c r="R13" i="25"/><c r="R14" i="25"/><c r="R15" i="25"/><c r="R16" i="25"/><c r="R17" i="25"/><c r="R18" i="25"/><c r="K13" i="25"/><c r="K14" i="25"/><c r="K15" i="25"/><c r="K16" i="25"/><c r="K17" i="25"/><c r="K18" i="25"/><c r="W13" i="25"/><c r="W14" i="25"/><c r="W15" i="25"/><c r="W16" i="25"/><c r="W17" i="25"/><c r="W18" i="25"/><c r="U13" i="25"/><c r="U14" i="25"/><c r="U15" i="25"/><c r="U16" i="25"/><c r="U17" i="25"/><c r="U18" i="25"/><c r="T13" i="25"/><c r="T14" i="25"/><c r="T15" i="25"/><c r="T16" i="25"/><c r="T17" i="25"/><c r="T18" i="25"/><c r="S13" i="25"/><c r="S14" i="25"/><c r="S15" i="25"/><c r="S16" i="25"/><c r="S17" i="25"/><c r="S18" i="25"/><c r="O13" i="25"/><c r="O14" i="25"/><c r="O15" i="25"/><c r="O16" i="25"/><c r="O17" i="25"/><c r="O18" i="25"/><c r="N13" i="25"/><c r="N14" i="25"/><c r="N15" i="25"/><c r="N16" i="25"/><c r="N17" i="25"/><c r="N18" i="25"/><c r="M13" i="25"/><c r="M14" i="25"/><c r="M15" i="25"/><c r="M16" i="25"/><c r="M17" i="25"/><c r="M18" i="25"/><c r="I13" i="25"/><c r="I14" i="25"/><c r="I15" i="25"/><c r="I16" i="25"/><c r="I17" i="25"/><c r="I18" i="25"/><c r="H13" i="25"/><c r="H14" i="25"/><c r="H15" i="25"/><c r="H16" i="25"/><c r="H17" i="25"/><c r="H18" i="25"/><c r="E13" i="25"/><c r="E14" i="25"/><c r="E15" i="25"/><c r="E16" i="25"/><c r="E17" i="25"/><c r="E18" i="25"/><c r="C13" i="25"/><c r="M20" i="24"/><c r="M21" i="24" s="1"/><c r="U20" i="24"/><c r="AB18" i="24"/><c r="AB19" i="24"/><c r="AB20" i="24"/><c r="AB21" i="24"/><c r="V14" i="24"/><c r="V15" i="24" s="1"/><c r="V16" i="24" s="1"/><c r="V17" i="24" s="1"/><c r="V18" i="24" s="1"/><c r="V19" i="24" s="1"/><c r="V20" i="24" s="1"/><c r="V21" i="24" s="1"/><c r="S14" i="24"/><c r="S15" i="24"/><c r="S16" i="24"/><c r="S17" i="24"/><c r="S18" i="24"/><c r="S19" i="24"/><c r="S20" i="24"/><c r="S21" i="24"/><c r="H13" i="24"/><c r="H14" i="24" s="1"/><c r="H15" i="24" s="1"/><c r="H16" i="24" s="1"/><c r="H17" i="24" s="1"/><c r="H18" i="24" s="1"/><c r="H19" i="24" s="1"/><c r="H20" i="24" s="1"/><c r="H21" i="24" s="1"/><c r="AB12" i="24"/><c r="AB13" i="24"/><c r="AB14" i="24"/><c r="AB15" i="24"/><c r="AB16" i="24"/><c r="AA12" i="24"/><c r="AA13" i="24" s="1"/><c r="AA14" i="24" s="1"/><c r="AA15" i="24" s="1"/><c r="AA16" i="24" s="1"/><c r="AA17" i="24" s="1"/><c r="AA18" i="24" s="1"/><c r="AA19" i="24" s="1"/><c r="AA20" i="24" s="1"/><c r="AA21" i="24" s="1"/><c r="Z12" i="24"/><c r="Z13" i="24" s="1"/><c r="Z14" i="24" s="1"/><c r="Z15" i="24" s="1"/><c r="Z16" i="24" s="1"/><c r="Z17" i="24" s="1"/><c r="Z18" i="24" s="1"/><c r="Z19" i="24" s="1"/><c r="Z20" i="24" s="1"/><c r="Z21" i="24" s="1"/><c r="Y12" i="24"/><c r="Y13" i="24" s="1"/><c r="Y14" i="24" s="1"/><c r="Y15" i="24" s="1"/><c r="Y16" i="24" s="1"/><c r="Y17" i="24" s="1"/><c r="Y18" i="24" s="1"/><c r="Y19" i="24" s="1"/><c r="Y20" i="24" s="1"/><c r="Y21" i="24" s="1"/><c r="V12" i="24"/><c r="V13" i="24" s="1"/><c r="T12" i="24"/><c r="T13" i="24" s="1"/><c r="T14" i="24" s="1"/><c r="T15" i="24" s="1"/><c r="T16" i="24" s="1"/><c r="T17" i="24" s="1"/><c r="T18" i="24" s="1"/><c r="T19" i="24" s="1"/><c r="T20" i="24" s="1"/><c r="T21" i="24" s="1"/><c r="S12" i="24"/><c r="S13" i="24"/><c r="N12" i="24"/><c r="N13" i="24" s="1"/><c r="N14" i="24" s="1"/><c r="N15" i="24" s="1"/><c r="N16" i="24" s="1"/><c r="N17" i="24" s="1"/><c r="N18" i="24" s="1"/><c r="N19" i="24" s="1"/><c r="N20" i="24" s="1"/><c r="N21" i="24" s="1"/><c r="K12" i="24"/><c r="K13" i="24" s="1"/><c r="K14" i="24" s="1"/><c r="K15" i="24" s="1"/><c r="K16" i="24" s="1"/><c r="K17" i="24" s="1"/><c r="K18" i="24" s="1"/><c r="K19" i="24" s="1"/><c r="K20" i="24" s="1"/><c r="K21" i="24" s="1"/><c r="D12" i="24"/><c r="D13" i="24" s="1"/><c r="D14" i="24" s="1"/><c r="D15" i="24" s="1"/><c r="D16" i="24" s="1"/><c r="D17" i="24" s="1"/><c r="D18" i="24" s="1"/><c r="D19" i="24" s="1"/><c r="D20" i="24" s="1"/><c r="D21" i="24" s="1"/></calcChain>